MANIFEST.in
README.org
setup.py
micropy/__init__.py
micropy/__init__.pyi
micropy/bintools.py
micropy/bintools.pyi
micropy/dig.py
micropy/dig.pyi
micropy/fsm.py
micropy/fsm.pyi
micropy/lang.py
micropy/lang.pyi
micropy/microscope.py
micropy/microscope.pyi
micropy/pipelib.py
micropy/pipelib.pyi
micropy/primitives.py
micropy/primitives.pyi
micropy/testing.py
micropy/testing.pyi
micropy/view.py
micropy/view.pyi
micropy.egg-info/PKG-INFO
micropy.egg-info/SOURCES.txt
micropy.egg-info/dependency_links.txt
micropy.egg-info/requires.txt
micropy.egg-info/top_level.txt